pjdev_excel/__about__.py
pjdev_excel/__init__.py
pjdev_excel/models.py
pjdev_excel/service.py
pjdev_excel/utilities.py
pjdev_excel-4.6.3.dist-info/METADATA
pjdev_excel-4.6.3.dist-info/WHEEL
pjdev_excel-4.6.3.dist-info/licenses/LICENSE.txt
pjdev_excel-4.6.3.dist-info/RECORD
