Metadata-Version: 2.4
Name: pjdev-excel
Version: 4.6.3
Author-email: Purple Jay LLC <apps+keystone-python-221-issue-@purplejay.io>
License-Expression: MIT
License-File: LICENSE.txt
Classifier: Development Status :: 4 - Beta
Classifier: Programming Language :: Python
Classifier: Programming Language :: Python :: 3.12
Classifier: Programming Language :: Python :: Implementation :: CPython
Classifier: Programming Language :: Python :: Implementation :: PyPy
Requires-Python: >=3.12
Requires-Dist: openpyxl
Requires-Dist: pydantic
